Workbook

Sheet Instructions
B2: OCR vs Gemini Spot Check — Home Assessment Extraction
B4: Purpose
B5: Manually verify a sample of fields where Cloud Vision and Gemini disagreed, to (1) confirm Gemini should be the trusted primary extractor and (2) find which columns need mandatory manual review at production scale.
B7: Sample
B8: 30 files total: 20 with the most Cloud Vision/Gemini disagreements ("Bad OCR") + 10 random files, pulled from the 60-file pilot batch. This mixes worst-case failure patterns with a realistic baseline.
B10: How to fill in the 'Spot Check' tab
B11: 1. Open the source PDF for each Source File (pilot_scans_1/2/3 folders).
B12: 2. Read the field directly from the scan and type the true value into the yellow 'Correct Value' column.
B13: 3. Leave 'Correct Value' blank only if the field is genuinely illegible on the scan.
B14: 4. 'Gemini Match?' and 'Cloud Vision Match?' fill in automatically once you type the Correct Value.
B16: How to read the 'Summary by Field' tab
B17: Match rate = % of spot-checked rows where that source's value equals your Correct Value. Any field below the review threshold (cell B2, default 90%) is flagged for mandatory manual review in production.
... B21: - A row here only exists where Cloud Vision and Gemini disagreed — fields where both models already agreed are not in this sample and are assumed correct for this exercise.

Sheet Spot Check
A1: Sample Group | B1: Source File | C1: Section | D1: Field | E1: Cloud Vision Value | F1: Gemini Value | G1: Correct Value (fill in) | H1: Gemini Match? | I1: Cloud Vision Match? | J1: Reviewer Notes
A2: Bad OCR | B2: Sedakhoreni_Sinanyan_-_In_Home_Assessment_10-22-25.pdf | C2: Behavioral Observations | D2: Agitation/Aggression: Does the patient get angry or hostile | F2: Yes | H2: =IF($G2="","",IF(LOWER(TRIM($G2))=LOWER(TRIM($F2)),"Match","Mismatch")) | I2: =IF($G2="","",IF(LOWER(TRIM($G2))=LOWER(TRIM($E2)),"Match","Mismatch"))
A3: Bad OCR | B3: Sedakhoreni_Sinanyan_-_In_Home_Assessment_10-22-25.pdf | C3: Behavioral Observations | D3: Anxiety/Shadowing: Does the patient routinely follow around their caregiver | F3: No | H3: =IF($G3="","",IF(LOWER(TRIM($G3))=LOWER(TRIM($F3)),"Match","Mismatch")) | I3: =IF($G3="","",IF(LOWER(TRIM($G3))=LOWER(TRIM($E3)),"Match","Mismatch"))
A4: Bad OCR | B4: Sedakhoreni_Sinanyan_-_In_Home_Assessment_10-22-25.pdf | C4: Behavioral Observations | D4: Hallucinations: Does the patient see and/or hear things that no one else can see or hear | F4: No | H4: =IF($G4="","",IF(LOWER(TRIM($G4))=LOWER(TRIM($F4)),"Match","Mismatch")) | I4: =IF($G4="","",IF(LOWER(TRIM($G4))=LOWER(TRIM($E4)),"Match","Mismatch"))
A5: Bad OCR | B5: Sedakhoreni_Sinanyan_-_In_Home_Assessment_10-22-25.pdf | C5: Behavioral Observations | D5: Indifference/Social Withdrawal: Does the patient seem less interested in their usual activities | F5: Yes | H5: =IF($G5="","",IF(LOWER(TRIM($G5))=LOWER(TRIM($F5)),"Match","Mismatch")) | I5: =IF($G5="","",IF(LOWER(TRIM($G5))=LOWER(TRIM($E5)),"Match","Mismatch"))
A6: Bad OCR | B6: Sedakhoreni_Sinanyan_-_In_Home_Assessment_10-22-25.pdf | C6: Behavioral Observations | D6: Irritability/Moodiness: Does the patient act impatient | F6: No | H6: =IF($G6="","",IF(LOWER(TRIM($G6))=LOWER(TRIM($F6)),"Match","Mismatch")) | I6: =IF($G6="","",IF(LOWER(TRIM($G6))=LOWER(TRIM($E6)),"Match","Mismatch"))
A7: Bad OCR | B7: Sedakhoreni_Sinanyan_-_In_Home_Assessment_10-22-25.pdf | C7: Behavioral Observations | D7: Other Behavioral Observations | F7: quiet & likes to just sit | H7: =IF($G7="","",IF(LOWER(TRIM($G7))=LOWER(TRIM($F7)),"Match","Mismatch")) | I7: =IF($G7="","",IF(LOWER(TRIM($G7))=LOWER(TRIM($E7)),"Match","Mismatch"))
A8: Bad OCR | B8: Sedakhoreni_Sinanyan_-_In_Home_Assessment_10-22-25.pdf | C8: Behavioral Observations | D8: Sleep Problems: Does the patient have trouble sleeping at night | F8: No | H8: =IF($G8="","",IF(LOWER(TRIM($G8))=LOWER(TRIM($F8)),"Match","Mismatch")) | I8: =IF($G8="","",IF(LOWER(TRIM($G8))=LOWER(TRIM($E8)),"Match","Mismatch"))
A9: Bad OCR | B9: Sedakhoreni_Sinanyan_-_In_Home_Assessment_10-22-25.pdf | C9: Behavioral Observations | D9: Suspiciousness/Paranoia: Is the patient suspicious without good reason | F9: No | H9: =IF($G9="","",IF(LOWER(TRIM($G9))=LOWER(TRIM($F9)),"Match","Mismatch")) | I9: =IF($G9="","",IF(LOWER(TRIM($G9))=LOWER(TRIM($E9)),"Match","Mismatch"))
A10: Bad OCR | B10: Sedakhoreni_Sinanyan_-_In_Home_Assessment_10-22-25.pdf | C10: Daily Function (rating scale) | D10: Bathing | F10: requires_assistance | H10: =IF($G10="","",IF(LOWER(TRIM($G10))=LOWER(TRIM($F10)),"Match","Mismatch")) | I10: =IF($G10="","",IF(LOWER(TRIM($G10))=LOWER(TRIM($E10)),"Match","Mismatch"))
A11: Bad OCR | B11: Sedakhoreni_Sinanyan_-_In_Home_Assessment_10-22-25.pdf | C11: Daily Function (rating scale) | D11: Continence (control of bladder and bowels) | F11: completely_independent | H11: =IF($G11="","",IF(LOWER(TRIM($G11))=LOWER(TRIM($F11)),"Match","Mismatch")) | I11: =IF($G11="","",IF(LOWER(TRIM($G11))=LOWER(TRIM($E11)),"Match","Mismatch"))
A12: Bad OCR | B12: Sedakhoreni_Sinanyan_-_In_Home_Assessment_10-22-25.pdf | C12: Daily Function (rating scale) | D12: Dressing (including getting clothes from drawers or closet) | F12: requires_assistance | H12: =IF($G12="","",IF(LOWER(TRIM($G12))=LOWER(TRIM($F12)),"Match","Mismatch")) | I12: =IF($G12="","",IF(LOWER(TRIM($G12))=LOWER(TRIM($E12)),"Match","Mismatch"))
A13: Bad OCR | B13: Sedakhoreni_Sinanyan_-_In_Home_Assessment_10-22-25.pdf | C13: Daily Function (rating scale) | D13: Driving or using public transportation | F13: cannot_do_at_all | H13: =IF($G13="","",IF(LOWER(TRIM($G13))=LOWER(TRIM($F13)),"Match","Mismatch")) | I13: =IF($G13="","",IF(LOWER(TRIM($G13))=LOWER(TRIM($E13)),"Match","Mismatch"))
... A34: Bad OCR | B34: Sedakhoreni_Sinanyan_-_In_Home_Assessment_10-22-25.pdf | C34: Header / Identifying Info | D34: Date of Birth: | F34: 7/1/1958 | H34: =IF($G34="","",IF(LOWER(TRIM($G34))=LOWER(TRIM($F34)),"Match","Mismatch")) | I34: =IF($G34="","",IF(LOWER(TRIM($G34))=LOWER(TRIM($E34)),"Match","Mismatch"))
A35: Bad OCR | B35: Sedakhoreni_Sinanyan_-_In_Home_Assessment_10-22-25.pdf | C35: Header / Identifying Info | D35: In-Home Assessment Date: | E35: / N ) 14 Are walkways clear of tripping hazards , rugs , cords , and excessive clutter ? ( Y / N ) 15 Is the lighting in the home fairly bright or dim side ? 16 If stairs are accessible , are they free of bright lighting ? ( Y / N ) 17 Is the bathroom equipped with mobility as grab bars , shower chair , toilet riser ? ( Y / 18 Does the patient have access to the kitchen - If kitchen access , which appliance ( s ) is able to use independently ? ( e.g.- microwave toaster / toaster oven , stove top , oven , etc. - If no kitchen access , please include details how patient gets food / drink , how they're restricted , etc. 19 Have safety knobs or an automatic shut - off installed on the stove ? ( Y / N ) 20 Are medications clearly labeled ? ( Y / N ) | F35: 10/22 | H35: =IF($G35="","",IF(LOWER(TRIM($G35))=LOWER(TRIM($F35)),"Match","Mismatch")) | I35: =IF($G35="","",IF(LOWER(TRIM($G35))=LOWER(TRIM($E35)),"Match","Mismatch"))
A36: Bad OCR | B36: Sedakhoreni_Sinanyan_-_In_Home_Assessment_10-22-25.pdf | C36: Header / Identifying Info | D36: Medicare Identification Number: | F36: 1m31f96ch 28 | H36: =IF($G36="","",IF(LOWER(TRIM($G36))=LOWER(TRIM($F36)),"Match","Mismatch")) | I36: =IF($G36="","",IF(LOWER(TRIM($G36))=LOWER(TRIM($E36)),"Match","Mismatch"))
A37: Bad OCR | B37: Sedakhoreni_Sinanyan_-_In_Home_Assessment_10-22-25.pdf | C37: Header / Identifying Info | D37: Name of Patient: | F37: Sedakhoreni Sinanyan | H37: =IF($G37="","",IF(LOWER(TRIM($G37))=LOWER(TRIM($F37)),"Match","Mismatch")) | I37: =IF($G37="","",IF(LOWER(TRIM($G37))=LOWER(TRIM($E37)),"Match","Mismatch"))
A38: Bad OCR | B38: Sedakhoreni_Sinanyan_-_In_Home_Assessment_10-22-25.pdf | C38: Header / Identifying Info | D38: Performed by: | F38: Jyoti Suhag | H38: =IF($G38="","",IF(LOWER(TRIM($G38))=LOWER(TRIM($F38)),"Match","Mismatch")) | I38: =IF($G38="","",IF(LOWER(TRIM($G38))=LOWER(TRIM($E38)),"Match","Mismatch"))
A39: Bad OCR | B39: Sedakhoreni_Sinanyan_-_In_Home_Assessment_10-22-25.pdf | C39: Header / Identifying Info | D39: Referral Date: | F39: 10/7 | H39: =IF($G39="","",IF(LOWER(TRIM($G39))=LOWER(TRIM($F39)),"Match","Mismatch")) | I39: =IF($G39="","",IF(LOWER(TRIM($G39))=LOWER(TRIM($E39)),"Match","Mismatch"))
A40: Bad OCR | B40: In Home Assessment - First Smile -1.pdf | C40: Behavioral Observations | D40: Agitation/Aggression: Does the patient get angry or hostile | E40: Yes | F40: No | H40: =IF($G40="","",IF(LOWER(TRIM($G40))=LOWER(TRIM($F40)),"Match","Mismatch")) | I40: =IF($G40="","",IF(LOWER(TRIM($G40))=LOWER(TRIM($E40)),"Match","Mismatch"))
A41: Bad OCR | B41: In Home Assessment - First Smile -1.pdf | C41: Behavioral Observations | D41: Anxiety/Shadowing: Does the patient routinely follow around their caregiver | F41: No | H41: =IF($G41="","",IF(LOWER(TRIM($G41))=LOWER(TRIM($F41)),"Match","Mismatch")) | I41: =IF($G41="","",IF(LOWER(TRIM($G41))=LOWER(TRIM($E41)),"Match","Mismatch"))
A42: Bad OCR | B42: In Home Assessment - First Smile -1.pdf | C42: Behavioral Observations | D42: Hallucinations: Does the patient see and/or hear things that no one else can see or hear | E42: Yes | F42: No | H42: =IF($G42="","",IF(LOWER(TRIM($G42))=LOWER(TRIM($F42)),"Match","Mismatch")) | I42: =IF($G42="","",IF(LOWER(TRIM($G42))=LOWER(TRIM($E42)),"Match","Mismatch"))
A43: Bad OCR | B43: In Home Assessment - First Smile -1.pdf | C43: Behavioral Observations | D43: Indifference/Social Withdrawal: Does the patient seem less interested in their usual activities | F43: No | H43: =IF($G43="","",IF(LOWER(TRIM($G43))=LOWER(TRIM($F43)),"Match","Mismatch")) | I43: =IF($G43="","",IF(LOWER(TRIM($G43))=LOWER(TRIM($E43)),"Match","Mismatch"))
A44: Bad OCR | B44: In Home Assessment - First Smile -1.pdf | C44: Behavioral Observations | D44: Irritability/Moodiness: Does the patient act impatient | E44: Yes | F44: No | H44: =IF($G44="","",IF(LOWER(TRIM($G44))=LOWER(TRIM($F44)),"Match","Mismatch")) | I44: =IF($G44="","",IF(LOWER(TRIM($G44))=LOWER(TRIM($E44)),"Match","Mismatch"))
A45: Bad OCR | B45: In Home Assessment - First Smile -1.pdf | C45: Behavioral Observations | D45: Sleep Problems: Does the patient have trouble sleeping at night | F45: No | H45: =IF($G45="","",IF(LOWER(TRIM($G45))=LOWER(TRIM($F45)),"Match","Mismatch")) | I45: =IF($G45="","",IF(LOWER(TRIM($G45))=LOWER(TRIM($E45)),"Match","Mismatch"))
A46: Bad OCR | B46: In Home Assessment - First Smile -1.pdf | C46: Behavioral Observations | D46: Suspiciousness/Paranoia: Is the patient suspicious without good reason | E46: Yes | F46: No | H46: =IF($G46="","",IF(LOWER(TRIM($G46))=LOWER(TRIM($F46)),"Match","Mismatch")) | I46: =IF($G46="","",IF(LOWER(TRIM($G46))=LOWER(TRIM($E46)),"Match","Mismatch"))
A47: Bad OCR | B47: In Home Assessment - First Smile -1.pdf | C47: Daily Function (rating scale) | D47: Bathing | F47: completely_independent | H47: =IF($G47="","",IF(LOWER(TRIM($G47))=LOWER(TRIM($F47)),"Match","Mismatch")) | I47: =IF($G47="","",IF(LOWER(TRIM($G47))=LOWER(TRIM($E47)),"Match","Mismatch"))
A48: Bad OCR | B48: In Home Assessment - First Smile -1.pdf | C48: Daily Function (rating scale) | D48: Continence (control of bladder and bowels) | F48: requires_assistance | H48: =IF($G48="","",IF(LOWER(TRIM($G48))=LOWER(TRIM($F48)),"Match","Mismatch")) | I48: =IF($G48="","",IF(LOWER(TRIM($G48))=LOWER(TRIM($E48)),"Match","Mismatch"))
A49: Bad OCR | B49: In Home Assessment - First Smile -1.pdf | C49: Daily Function (rating scale) | D49: Dressing (including getting clothes from drawers or closet) | F49: requires_cueing_or_coaching | H49: =IF($G49="","",IF(LOWER(TRIM($G49))=LOWER(TRIM($F49)),"Match","Mismatch")) | I49: =IF($G49="","",IF(LOWER(TRIM($G49))=LOWER(TRIM($E49)),"Match","Mismatch"))
A50: Bad OCR | B50: In Home Assessment - First Smile -1.pdf | C50: Daily Function (rating scale) | D50: Driving or using public transportation | F50: cannot_do_at_all | H50: =IF($G50="","",IF(LOWER(TRIM($G50))=LOWER(TRIM($F50)),"Match","Mismatch")) | I50: =IF($G50="","",IF(LOWER(TRIM($G50))=LOWER(TRIM($E50)),"Match","Mismatch"))
A51: Bad OCR | B51: In Home Assessment - First Smile -1.pdf | C51: Daily Function (rating scale) | D51: Feeding | F51: requires_assistance | H51: =IF($G51="","",IF(LOWER(TRIM($G51))=LOWER(TRIM($F51)),"Match","Mismatch")) | I51: =IF($G51="","",IF(LOWER(TRIM($G51))=LOWER(TRIM($E51)),"Match","Mismatch"))
A52: Bad OCR | B52: In Home Assessment - First Smile -1.pdf | C52: Daily Function (rating scale) | D52: Finances | F52: cannot_do_at_all | H52: =IF($G52="","",IF(LOWER(TRIM($G52))=LOWER(TRIM($F52)),"Match","Mismatch")) | I52: =IF($G52="","",IF(LOWER(TRIM($G52))=LOWER(TRIM($E52)),"Match","Mismatch"))
A53: Bad OCR | B53: In Home Assessment - First Smile -1.pdf | C53: Daily Function (rating scale) | D53: Food Preparation | F53: cannot_do_at_all | H53: =IF($G53="","",IF(LOWER(TRIM($G53))=LOWER(TRIM($F53)),"Match","Mismatch")) | I53: =IF($G53="","",IF(LOWER(TRIM($G53))=LOWER(TRIM($E53)),"Match","Mismatch"))
A54: Bad OCR | B54: In Home Assessment - First Smile -1.pdf | C54: Daily Function (rating scale) | D54: Grooming (including teeth, hair, shaving, etc.) | F54: requires_assistance | H54: =IF($G54="","",IF(LOWER(TRIM($G54))=LOWER(TRIM($F54)),"Match","Mismatch")) | I54: =IF($G54="","",IF(LOWER(TRIM($G54))=LOWER(TRIM($E54)),"Match","Mismatch"))
A55: Bad OCR | B55: In Home Assessment - First Smile -1.pdf | C55: Daily Function (rating scale) | D55: Housekeeping | F55: cannot_do_at_all | H55: =IF($G55="","",IF(LOWER(TRIM($G55))=LOWER(TRIM($F55)),"Match","Mismatch")) | I55: =IF($G55="","",IF(LOWER(TRIM($G55))=LOWER(TRIM($E55)),"Match","Mismatch"))
A56: Bad OCR | B56: In Home Assessment - First Smile -1.pdf | C56: Daily Function (rating scale) | D56: Laundry | F56: cannot_do_at_all | H56: =IF($G56="","",IF(LOWER(TRIM($G56))=LOWER(TRIM($F56)),"Match","Mismatch")) | I56: =IF($G56="","",IF(LOWER(TRIM($G56))=LOWER(TRIM($E56)),"Match","Mismatch"))
A57: Bad OCR | B57: In Home Assessment - First Smile -1.pdf | C57: Daily Function (rating scale) | D57: Medication Management | F57: cannot_do_at_all | H57: =IF($G57="","",IF(LOWER(TRIM($G57))=LOWER(TRIM($F57)),"Match","Mismatch")) | I57: =IF($G57="","",IF(LOWER(TRIM($G57))=LOWER(TRIM($E57)),"Match","Mismatch"))
A58: Bad OCR | B58: In Home Assessment - First Smile -1.pdf | C58: Daily Function (rating scale) | D58: Shopping | F58: cannot_do_at_all | H58: =IF($G58="","",IF(LOWER(TRIM($G58))=LOWER(TRIM($F58)),"Match","Mismatch")) | I58: =IF($G58="","",IF(LOWER(TRIM($G58))=LOWER(TRIM($E58)),"Match","Mismatch"))
... A61: Bad OCR | B61: In Home Assessment - First Smile -1.pdf | C61: Daily Function (rating scale) | D61: Use the Telephone | F61: requires_cueing_or_coaching | H61: =IF($G61="","",IF(LOWER(TRIM($G61))=LOWER(TRIM($F61)),"Match","Mismatch")) | I61: =IF($G61="","",IF(LOWER(TRIM($G61))=LOWER(TRIM($E61)),"Match","Mismatch"))
A62: Bad OCR | B62: In Home Assessment - First Smile -1.pdf | C62: Environmental / Social | D62: Has the patient fallen in the last year | E62: Yes | F62: No | H62: =IF($G62="","",IF(LOWER(TRIM($G62))=LOWER(TRIM($F62)),"Match","Mismatch")) | I62: =IF($G62="","",IF(LOWER(TRIM($G62))=LOWER(TRIM($E62)),"Match","Mismatch"))
A63: Bad OCR | B63: In Home Assessment - First Smile -1.pdf | C63: Environmental / Social | D63: Is the patient at risk for food insecurity or poor nutrition | E63: Yes | F63: No | H63: =IF($G63="","",IF(LOWER(TRIM($G63))=LOWER(TRIM($F63)),"Match","Mismatch")) | I63: =IF($G63="","",IF(LOWER(TRIM($G63))=LOWER(TRIM($E63)),"Match","Mismatch"))
A64: Bad OCR | B64: In Home Assessment - First Smile -1.pdf | C64: Environmental / Social | D64: Is the patient at risk for housing insecurity | E64: Yes | F64: No | H64: =IF($G64="","",IF(LOWER(TRIM($G64))=LOWER(TRIM($F64)),"Match","Mismatch")) | I64: =IF($G64="","",IF(LOWER(TRIM($G64))=LOWER(TRIM($E64)),"Match","Mismatch"))
A65: Bad OCR | B65: In Home Assessment - First Smile -1.pdf | C65: Environmental / Social | D65: Other Environmental/Social Observations | E65: yes cameras installed in the living room and the bedroek , ر ہونے کی recommended tire extinguisher installment ? ho ho No AO по caregiver is attentive Mo | F65: caregiver is attentive | H65: =IF($G65="","",IF(LOWER(TRIM($G65))=LOWER(TRIM($F65)),"Match","Mismatch")) | I65: =IF($G65="","",IF(LOWER(TRIM($G65))=LOWER(TRIM($E65)),"Match","Mismatch"))
A66: Bad OCR | B66: In Home Assessment - First Smile -1.pdf | C66: Environmental / Social | D66: Is the patient socially isolated outside of their normal behaviors | E66: Yes | F66: No | H66: =IF($G66="","",IF(LOWER(TRIM($G66))=LOWER(TRIM($F66)),"Match","Mismatch")) | I66: =IF($G66="","",IF(LOWER(TRIM($G66))=LOWER(TRIM($E66)),"Match","Mismatch"))
A67: Bad OCR | B67: In Home Assessment - First Smile -1.pdf | C67: Environmental / Social | D67: Has the patient been targeted for exploitation or scamming | E67: Yes | F67: No | H67: =IF($G67="","",IF(LOWER(TRIM($G67))=LOWER(TRIM($F67)),"Match","Mismatch")) | I67: =IF($G67="","",IF(LOWER(TRIM($G67))=LOWER(TRIM($E67)),"Match","Mismatch"))
A68: Bad OCR | B68: In Home Assessment - First Smile -1.pdf | C68: Final Observations | D68: Any other observations or concerns | E68: suggests caregiver is attentive ; however patient's care needs exceed what one caregiver . manage alone . support would benefit both | F68: Observation suggests caregiver is attentive and caring; however patient's care needs appear to exceed what one caregiver can sustainably manage alone. Additional support would benefit both patient safety and caregiver well-being | H68: =IF($G68="","",IF(LOWER(TRIM($G68))=LOWER(TRIM($F68)),"Match","Mismatch")) | I68: =IF($G68="","",IF(LOWER(TRIM($G68))=LOWER(TRIM($E68)),"Match","Mismatch"))
A69: Bad OCR | B69: In Home Assessment - First Smile -1.pdf | C69: Header / Identifying Info | D69: Address: | E69: 12/10 11/20 Anush Suren Hayrapetian 9/3/1937 91A 16TH 1069son son Ave # 3 , Glemadale CA 91201 | F69: 1060 Elm Ave #3, Glendale CA 91201 | H69: =IF($G69="","",IF(LOWER(TRIM($G69))=LOWER(TRIM($F69)),"Match","Mismatch")) | I69: =IF($G69="","",IF(LOWER(TRIM($G69))=LOWER(TRIM($E69)),"Match","Mismatch"))
A70: Bad OCR | B70: In Home Assessment - First Smile -1.pdf | C70: Header / Identifying Info | D70: Answers provided by: | E70: busine Chakaian apartment reut patient lives alone , but 1967 family ? independently yes | F70: Lusine Chakaian | H70: =IF($G70="","",IF(LOWER(TRIM($G70))=LOWER(TRIM($F70)),"Match","Mismatch")) | I70: =IF($G70="","",IF(LOWER(TRIM($G70))=LOWER(TRIM($E70)),"Match","Mismatch"))
A71: Bad OCR | B71: In Home Assessment - First Smile -1.pdf | C71: Header / Identifying Info | D71: Date of Birth: | E71: 12/10 11/20 Anush Suren Hayrapetian 9/3/1937 91A 16TH 1069son son Ave # 3 , Glemadale CA 91201 | F71: 8/9/1937 | H71: =IF($G71="","",IF(LOWER(TRIM($G71))=LOWER(TRIM($F71)),"Match","Mismatch")) | I71: =IF($G71="","",IF(LOWER(TRIM($G71))=LOWER(TRIM($E71)),"Match","Mismatch"))
A72: Bad OCR | B72: In Home Assessment - First Smile -1.pdf | C72: Header / Identifying Info | D72: In-Home Assessment Date: | E72: 12/10 11/20 Anush Suren Hayrapetian 9/3/1937 91A 16TH 1069son son Ave # 3 , Glemadale CA 91201 | F72: 12/10/2025 | H72: =IF($G72="","",IF(LOWER(TRIM($G72))=LOWER(TRIM($F72)),"Match","Mismatch")) | I72: =IF($G72="","",IF(LOWER(TRIM($G72))=LOWER(TRIM($E72)),"Match","Mismatch"))
A73: Bad OCR | B73: In Home Assessment - First Smile -1.pdf | C73: Header / Identifying Info | D73: Medicare Identification Number: | E73: 12/10 11/20 Anush Suren Hayrapetian 9/3/1937 91A 16TH 1069son son Ave # 3 , Glemadale CA 91201 | F73: 2091A16TT 28 | H73: =IF($G73="","",IF(LOWER(TRIM($G73))=LOWER(TRIM($F73)),"Match","Mismatch")) | I73: =IF($G73="","",IF(LOWER(TRIM($G73))=LOWER(TRIM($E73)),"Match","Mismatch"))
... A76: Bad OCR | B76: In Home Assessment - First Smile -1.pdf | C76: Header / Identifying Info | D76: Referral Date: | E76: 12/10 11/20 Anush Suren Hayrapetian 9/3/1937 91A 16TH 1069son son Ave # 3 , Glemadale CA 91201 | F76: 11/20/2025 | H76: =IF($G76="","",IF(LOWER(TRIM($G76))=LOWER(TRIM($F76)),"Match","Mismatch")) | I76: =IF($G76="","",IF(LOWER(TRIM($G76))=LOWER(TRIM($E76)),"Match","Mismatch"))
A77: Bad OCR | B77: Karapet_Markar_-_in_home_assessment.pdf | C77: Behavioral Observations | D77: Agitation/Aggression: Does the patient get angry or hostile | F77: No | H77: =IF($G77="","",IF(LOWER(TRIM($G77))=LOWER(TRIM($F77)),"Match","Mismatch")) | I77: =IF($G77="","",IF(LOWER(TRIM($G77))=LOWER(TRIM($E77)),"Match","Mismatch"))
A78: Bad OCR | B78: Karapet_Markar_-_in_home_assessment.pdf | C78: Behavioral Observations | D78: Anxiety/Shadowing: Does the patient routinely follow around their caregiver | F78: No | H78: =IF($G78="","",IF(LOWER(TRIM($G78))=LOWER(TRIM($F78)),"Match","Mismatch")) | I78: =IF($G78="","",IF(LOWER(TRIM($G78))=LOWER(TRIM($E78)),"Match","Mismatch"))
A79: Bad OCR | B79: Karapet_Markar_-_in_home_assessment.pdf | C79: Behavioral Observations | D79: Hallucinations: Does the patient see and/or hear things that no one else can see or hear | F79: No | H79: =IF($G79="","",IF(LOWER(TRIM($G79))=LOWER(TRIM($F79)),"Match","Mismatch")) | I79: =IF($G79="","",IF(LOWER(TRIM($G79))=LOWER(TRIM($E79)),"Match","Mismatch"))
A80: Bad OCR | B80: Karapet_Markar_-_in_home_assessment.pdf | C80: Behavioral Observations | D80: Indifference/Social Withdrawal: Does the patient seem less interested in their usual activities | F80: No | H80: =IF($G80="","",IF(LOWER(TRIM($G80))=LOWER(TRIM($F80)),"Match","Mismatch")) | I80: =IF($G80="","",IF(LOWER(TRIM($G80))=LOWER(TRIM($E80)),"Match","Mismatch"))
A81: Bad OCR | B81: Karapet_Markar_-_in_home_assessment.pdf | C81: Behavioral Observations | D81: Irritability/Moodiness: Does the patient act impatient | F81: No | H81: =IF($G81="","",IF(LOWER(TRIM($G81))=LOWER(TRIM($F81)),"Match","Mismatch")) | I81: =IF($G81="","",IF(LOWER(TRIM($G81))=LOWER(TRIM($E81)),"Match","Mismatch"))
A82: Bad OCR | B82: Karapet_Markar_-_in_home_assessment.pdf | C82: Behavioral Observations | D82: Other Behavioral Observations | E82: по по по religious beliefs appear to provide comfort to the patient | F82: religious beliefs appear to provide comfort to the patient | H82: =IF($G82="","",IF(LOWER(TRIM($G82))=LOWER(TRIM($F82)),"Match","Mismatch")) | I82: =IF($G82="","",IF(LOWER(TRIM($G82))=LOWER(TRIM($E82)),"Match","Mismatch"))
A83: Bad OCR | B83: Karapet_Markar_-_in_home_assessment.pdf | C83: Behavioral Observations | D83: Sleep Problems: Does the patient have trouble sleeping at night | F83: No | H83: =IF($G83="","",IF(LOWER(TRIM($G83))=LOWER(TRIM($F83)),"Match","Mismatch")) | I83: =IF($G83="","",IF(LOWER(TRIM($G83))=LOWER(TRIM($E83)),"Match","Mismatch"))
A84: Bad OCR | B84: Karapet_Markar_-_in_home_assessment.pdf | C84: Behavioral Observations | D84: Suspiciousness/Paranoia: Is the patient suspicious without good reason | F84: No | H84: =IF($G84="","",IF(LOWER(TRIM($G84))=LOWER(TRIM($F84)),"Match","Mismatch")) | I84: =IF($G84="","",IF(LOWER(TRIM($G84))=LOWER(TRIM($E84)),"Match","Mismatch"))
A85: Bad OCR | B85: Karapet_Markar_-_in_home_assessment.pdf | C85: Daily Function (rating scale) | D85: Bathing | F85: completely_independent | H85: =IF($G85="","",IF(LOWER(TRIM($G85))=LOWER(TRIM($F85)),"Match","Mismatch")) | I85: =IF($G85="","",IF(LOWER(TRIM($G85))=LOWER(TRIM($E85)),"Match","Mismatch"))
A86: Bad OCR | B86: Karapet_Markar_-_in_home_assessment.pdf | C86: Daily Function (rating scale) | D86: Continence (control of bladder and bowels) | F86: requires_assistance | H86: =IF($G86="","",IF(LOWER(TRIM($G86))=LOWER(TRIM($F86)),"Match","Mismatch")) | I86: =IF($G86="","",IF(LOWER(TRIM($G86))=LOWER(TRIM($E86)),"Match","Mismatch"))
A87: Bad OCR | B87: Karapet_Markar_-_in_home_assessment.pdf | C87: Daily Function (rating scale) | D87: Dressing (including getting clothes from drawers or closet) | F87: completely_independent | H87: =IF($G87="","",IF(LOWER(TRIM($G87))=LOWER(TRIM($F87)),"Match","Mismatch")) | I87: =IF($G87="","",IF(LOWER(TRIM($G87))=LOWER(TRIM($E87)),"Match","Mismatch"))
A88: Bad OCR | B88: Karapet_Markar_-_in_home_assessment.pdf | C88: Daily Function (rating scale) | D88: Driving or using public transportation | F88: cannot_do_at_all | H88: =IF($G88="","",IF(LOWER(TRIM($G88))=LOWER(TRIM($F88)),"Match","Mismatch")) | I88: =IF($G88="","",IF(LOWER(TRIM($G88))=LOWER(TRIM($E88)),"Match","Mismatch"))
A89: Bad OCR | B89: Karapet_Markar_-_in_home_assessment.pdf | C89: Daily Function (rating scale) | D89: Feeding | F89: completely_independent | H89: =IF($G89="","",IF(LOWER(TRIM($G89))=LOWER(TRIM($F89)),"Match","Mismatch")) | I89: =IF($G89="","",IF(LOWER(TRIM($G89))=LOWER(TRIM($E89)),"Match","Mismatch"))
A90: Bad OCR | B90: Karapet_Markar_-_in_home_assessment.pdf | C90: Daily Function (rating scale) | D90: Finances | F90: requires_assistance | H90: =IF($G90="","",IF(LOWER(TRIM($G90))=LOWER(TRIM($F90)),"Match","Mismatch")) | I90: =IF($G90="","",IF(LOWER(TRIM($G90))=LOWER(TRIM($E90)),"Match","Mismatch"))
A91: Bad OCR | B91: Karapet_Markar_-_in_home_assessment.pdf | C91: Daily Function (rating scale) | D91: Food Preparation | F91: completely_independent | H91: =IF($G91="","",IF(LOWER(TRIM($G91))=LOWER(TRIM($F91)),"Match","Mismatch")) | I91: =IF($G91="","",IF(LOWER(TRIM($G91))=LOWER(TRIM($E91)),"Match","Mismatch"))
A92: Bad OCR | B92: Karapet_Markar_-_in_home_assessment.pdf | C92: Daily Function (rating scale) | D92: Grooming (including teeth, hair, shaving, etc.) | F92: completely_independent | H92: =IF($G92="","",IF(LOWER(TRIM($G92))=LOWER(TRIM($F92)),"Match","Mismatch")) | I92: =IF($G92="","",IF(LOWER(TRIM($G92))=LOWER(TRIM($E92)),"Match","Mismatch"))
A93: Bad OCR | B93: Karapet_Markar_-_in_home_assessment.pdf | C93: Daily Function (rating scale) | D93: Housekeeping | F93: requires_assistance | H93: =IF($G93="","",IF(LOWER(TRIM($G93))=LOWER(TRIM($F93)),"Match","Mismatch")) | I93: =IF($G93="","",IF(LOWER(TRIM($G93))=LOWER(TRIM($E93)),"Match","Mismatch"))
A94: Bad OCR | B94: Karapet_Markar_-_in_home_assessment.pdf | C94: Daily Function (rating scale) | D94: Laundry | F94: requires_assistance | H94: =IF($G94="","",IF(LOWER(TRIM($G94))=LOWER(TRIM($F94)),"Match","Mismatch")) | I94: =IF($G94="","",IF(LOWER(TRIM($G94))=LOWER(TRIM($E94)),"Match","Mismatch"))
... A101: Bad OCR | B101: Karapet_Markar_-_in_home_assessment.pdf | C101: Environmental / Social | D101: Is the patient at risk for housing insecurity | F101: No | H101: =IF($G101="","",IF(LOWER(TRIM($G101))=LOWER(TRIM($F101)),"Match","Mismatch")) | I101: =IF($G101="","",IF(LOWER(TRIM($G101))=LOWER(TRIM($E101)),"Match","Mismatch"))
A102: Bad OCR | B102: Karapet_Markar_-_in_home_assessment.pdf | C102: Environmental / Social | D102: Other Environmental/Social Observations | E102: по yes has fallen last month no injuries patient trying to be . independant as much as | F102: patient trying to be. inde pendant as much al cau | H102: =IF($G102="","",IF(LOWER(TRIM($G102))=LOWER(TRIM($F102)),"Match","Mismatch")) | I102: =IF($G102="","",IF(LOWER(TRIM($G102))=LOWER(TRIM($E102)),"Match","Mismatch"))
A103: Bad OCR | B103: Karapet_Markar_-_in_home_assessment.pdf | C103: Environmental / Social | D103: Is the patient socially isolated outside of their normal behaviors | F103: No | H103: =IF($G103="","",IF(LOWER(TRIM($G103))=LOWER(TRIM($F103)),"Match","Mismatch")) | I103: =IF($G103="","",IF(LOWER(TRIM($G103))=LOWER(TRIM($E103)),"Match","Mismatch"))
A104: Bad OCR | B104: Karapet_Markar_-_in_home_assessment.pdf | C104: Environmental / Social | D104: Has the patient been targeted for exploitation or scamming | F104: No | H104: =IF($G104="","",IF(LOWER(TRIM($G104))=LOWER(TRIM($F104)),"Match","Mismatch")) | I104: =IF($G104="","",IF(LOWER(TRIM($G104))=LOWER(TRIM($E104)),"Match","Mismatch"))
A105: Bad OCR | B105: Karapet_Markar_-_in_home_assessment.pdf | C105: Final Observations | D105: Any other observations or concerns | E105: reports pain that may limit times , affecting independent requires assistance to maintain proper daily routine . | F105: Patient reports pain that may limit activity at times, affecting independent living and requires assistance to maintain safety and proper daily routine. | H105: =IF($G105="","",IF(LOWER(TRIM($G105))=LOWER(TRIM($F105)),"Match","Mismatch")) | I105: =IF($G105="","",IF(LOWER(TRIM($G105))=LOWER(TRIM($E105)),"Match","Mismatch"))
A106: Bad OCR | B106: Karapet_Markar_-_in_home_assessment.pdf | C106: Header / Identifying Info | D106: Address: | E106: 2/17/26 02/03/26 Anush Karabet Markar 07/01/1950 9H36KE 74V48 512 Concord St # 7 , Blendale , CA 91203 | F106: 512 Concord st #7, Glendale, CA 91203 | H106: =IF($G106="","",IF(LOWER(TRIM($G106))=LOWER(TRIM($F106)),"Match","Mismatch")) | I106: =IF($G106="","",IF(LOWER(TRIM($G106))=LOWER(TRIM($E106)),"Match","Mismatch"))
A107: Bad OCR | B107: Karapet_Markar_-_in_home_assessment.pdf | C107: Header / Identifying Info | D107: Answers provided by: | E107: 2/17/26 02/03/26 Anush Karabet Markar 07/01/1950 9H36KE 74V48 512 Concord St # 7 , Blendale , CA 91203 Karabet Markow condo rent by the family ? patient lives with his wife has a small dog ; house has stairs going to the 2nd floor room independently on the 2nd floor yes yes more on dim side Yes yes grab bars installed uses stove top to yes no Yes warm up his food . caregiver and his wife take eave of meal preparation standard stove | F107: Karabet Markar | H107: =IF($G107="","",IF(LOWER(TRIM($G107))=LOWER(TRIM($F107)),"Match","Mismatch")) | I107: =IF($G107="","",IF(LOWER(TRIM($G107))=LOWER(TRIM($E107)),"Match","Mismatch"))
A108: Bad OCR | B108: Karapet_Markar_-_in_home_assessment.pdf | C108: Header / Identifying Info | D108: Date of Birth: | E108: 2/17/26 02/03/26 Anush Karabet Markar 07/01/1950 9H36KE 74V48 | F108: 07/01/1950 | H108: =IF($G108="","",IF(LOWER(TRIM($G108))=LOWER(TRIM($F108)),"Match","Mismatch")) | I108: =IF($G108="","",IF(LOWER(TRIM($G108))=LOWER(TRIM($E108)),"Match","Mismatch"))
A109: Bad OCR | B109: Karapet_Markar_-_in_home_assessment.pdf | C109: Header / Identifying Info | D109: Medicare Identification Number: | F109: 9H36KE 7UV48 | H109: =IF($G109="","",IF(LOWER(TRIM($G109))=LOWER(TRIM($F109)),"Match","Mismatch")) | I109: =IF($G109="","",IF(LOWER(TRIM($G109))=LOWER(TRIM($E109)),"Match","Mismatch"))
A110: Bad OCR | B110: Karapet_Markar_-_in_home_assessment.pdf | C110: Header / Identifying Info | D110: Name of Patient: | E110: 2/17/26 02/03/26 Anush Karabet Markar | F110: Karabet Markar | H110: =IF($G110="","",IF(LOWER(TRIM($G110))=LOWER(TRIM($F110)),"Match","Mismatch")) | I110: =IF($G110="","",IF(LOWER(TRIM($G110))=LOWER(TRIM($E110)),"Match","Mismatch"))
A111: Bad OCR | B111: Karapet_Markar_-_in_home_assessment.pdf | C111: Header / Identifying Info | D111: Performed by: | E111: 2/17/26 02/03/26 Anush | F111: Anush | H111: =IF($G111="","",IF(LOWER(TRIM($G111))=LOWER(TRIM($F111)),"Match","Mismatch")) | I111: =IF($G111="","",IF(LOWER(TRIM($G111))=LOWER(TRIM($E111)),"Match","Mismatch"))
A112: Bad OCR | B112: Karapet_Markar_-_in_home_assessment.pdf | C112: Header / Identifying Info | D112: Referral Date: | E112: 2/17/26 02/03/26 | F112: 02/03/26 | H112: =IF($G112="","",IF(LOWER(TRIM($G112))=LOWER(TRIM($F112)),"Match","Mismatch")) | I112: =IF($G112="","",IF(LOWER(TRIM($G112))=LOWER(TRIM($E112)),"Match","Mismatch"))
A113: Bad OCR | B113: Hayganoush_Khodagholian.pdf | C113: Behavioral Observations | D113: Anxiety/Shadowing: Does the patient routinely follow around their caregiver | F113: No | H113: =IF($G113="","",IF(LOWER(TRIM($G113))=LOWER(TRIM($F113)),"Match","Mismatch")) | I113: =IF($G113="","",IF(LOWER(TRIM($G113))=LOWER(TRIM($E113)),"Match","Mismatch"))
A114: Bad OCR | B114: Hayganoush_Khodagholian.pdf | C114: Behavioral Observations | D114: Hallucinations: Does the patient see and/or hear things that no one else can see or hear | E114: Yes | F114: No | H114: =IF($G114="","",IF(LOWER(TRIM($G114))=LOWER(TRIM($F114)),"Match","Mismatch")) | I114: =IF($G114="","",IF(LOWER(TRIM($G114))=LOWER(TRIM($E114)),"Match","Mismatch"))
A115: Bad OCR | B115: Hayganoush_Khodagholian.pdf | C115: Behavioral Observations | D115: Indifference/Social Withdrawal: Does the patient seem less interested in their usual activities | F115: No | H115: =IF($G115="","",IF(LOWER(TRIM($G115))=LOWER(TRIM($F115)),"Match","Mismatch")) | I115: =IF($G115="","",IF(LOWER(TRIM($G115))=LOWER(TRIM($E115)),"Match","Mismatch"))
A116: Bad OCR | B116: Hayganoush_Khodagholian.pdf | C116: Behavioral Observations | D116: Other Behavioral Observations | E116: по Yes по putient displays inuctiona sensitivity | F116: patient displays emotional sensitivity | H116: =IF($G116="","",IF(LOWER(TRIM($G116))=LOWER(TRIM($F116)),"Match","Mismatch")) | I116: =IF($G116="","",IF(LOWER(TRIM($G116))=LOWER(TRIM($E116)),"Match","Mismatch"))
A117: Bad OCR | B117: Hayganoush_Khodagholian.pdf | C117: Behavioral Observations | D117: Sleep Problems: Does the patient have trouble sleeping at night | F117: Yes | H117: =IF($G117="","",IF(LOWER(TRIM($G117))=LOWER(TRIM($F117)),"Match","Mismatch")) | I117: =IF($G117="","",IF(LOWER(TRIM($G117))=LOWER(TRIM($E117)),"Match","Mismatch"))
A118: Bad OCR | B118: Hayganoush_Khodagholian.pdf | C118: Daily Function (rating scale) | D118: Bathing | F118: requires_cueing_or_coaching | H118: =IF($G118="","",IF(LOWER(TRIM($G118))=LOWER(TRIM($F118)),"Match","Mismatch")) | I118: =IF($G118="","",IF(LOWER(TRIM($G118))=LOWER(TRIM($E118)),"Match","Mismatch"))
A119: Bad OCR | B119: Hayganoush_Khodagholian.pdf | C119: Daily Function (rating scale) | D119: Continence (control of bladder and bowels) | F119: completely_independent | H119: =IF($G119="","",IF(LOWER(TRIM($G119))=LOWER(TRIM($F119)),"Match","Mismatch")) | I119: =IF($G119="","",IF(LOWER(TRIM($G119))=LOWER(TRIM($E119)),"Match","Mismatch"))
A120: Bad OCR | B120: Hayganoush_Khodagholian.pdf | C120: Daily Function (rating scale) | D120: Dressing (including getting clothes from drawers or closet) | F120: requires_cueing_or_coaching | H120: =IF($G120="","",IF(LOWER(TRIM($G120))=LOWER(TRIM($F120)),"Match","Mismatch")) | I120: =IF($G120="","",IF(LOWER(TRIM($G120))=LOWER(TRIM($E120)),"Match","Mismatch"))
A121: Bad OCR | B121: Hayganoush_Khodagholian.pdf | C121: Daily Function (rating scale) | D121: Driving or using public transportation | F121: cannot_do_at_all | H121: =IF($G121="","",IF(LOWER(TRIM($G121))=LOWER(TRIM($F121)),"Match","Mismatch")) | I121: =IF($G121="","",IF(LOWER(TRIM($G121))=LOWER(TRIM($E121)),"Match","Mismatch"))
A122: Bad OCR | B122: Hayganoush_Khodagholian.pdf | C122: Daily Function (rating scale) | D122: Feeding | F122: completely_independent | H122: =IF($G122="","",IF(LOWER(TRIM($G122))=LOWER(TRIM($F122)),"Match","Mismatch")) | I122: =IF($G122="","",IF(LOWER(TRIM($G122))=LOWER(TRIM($E122)),"Match","Mismatch"))
A123: Bad OCR | B123: Hayganoush_Khodagholian.pdf | C123: Daily Function (rating scale) | D123: Finances | F123: cannot_do_at_all | H123: =IF($G123="","",IF(LOWER(TRIM($G123))=LOWER(TRIM($F123)),"Match","Mismatch")) | I123: =IF($G123="","",IF(LOWER(TRIM($G123))=LOWER(TRIM($E123)),"Match","Mismatch"))
A124: Bad OCR | B124: Hayganoush_Khodagholian.pdf | C124: Daily Function (rating scale) | D124: Food Preparation | F124: requires_assistance | H124: =IF($G124="","",IF(LOWER(TRIM($G124))=LOWER(TRIM($F124)),"Match","Mismatch")) | I124: =IF($G124="","",IF(LOWER(TRIM($G124))=LOWER(TRIM($E124)),"Match","Mismatch"))
A125: Bad OCR | B125: Hayganoush_Khodagholian.pdf | C125: Daily Function (rating scale) | D125: Grooming (including teeth, hair, shaving, etc.) | F125: completely_independent | H125: =IF($G125="","",IF(LOWER(TRIM($G125))=LOWER(TRIM($F125)),"Match","Mismatch")) | I125: =IF($G125="","",IF(LOWER(TRIM($G125))=LOWER(TRIM($E125)),"Match","Mismatch"))
A126: Bad OCR | B126: Hayganoush_Khodagholian.pdf | C126: Daily Function (rating scale) | D126: Housekeeping | F126: requires_assistance | H126: =IF($G126="","",IF(LOWER(TRIM($G126))=LOWER(TRIM($F126)),"Match","Mismatch")) | I126: =IF($G126="","",IF(LOWER(TRIM($G126))=LOWER(TRIM($E126)),"Match","Mismatch"))
A127: Bad OCR | B127: Hayganoush_Khodagholian.pdf | C127: Daily Function (rating scale) | D127: Laundry | F127: requires_assistance | H127: =IF($G127="","",IF(LOWER(TRIM($G127))=LOWER(TRIM($F127)),"Match","Mismatch")) | I127: =IF($G127="","",IF(LOWER(TRIM($G127))=LOWER(TRIM($E127)),"Match","Mismatch"))
A128: Bad OCR | B128: Hayganoush_Khodagholian.pdf | C128: Daily Function (rating scale) | D128: Medication Management | F128: requires_assistance | H128: =IF($G128="","",IF(LOWER(TRIM($G128))=LOWER(TRIM($F128)),"Match","Mismatch")) | I128: =IF($G128="","",IF(LOWER(TRIM($G128))=LOWER(TRIM($E128)),"Match","Mismatch"))
... A132: Bad OCR | B132: Hayganoush_Khodagholian.pdf | C132: Daily Function (rating scale) | D132: Use the Telephone | F132: completely_independent | H132: =IF($G132="","",IF(LOWER(TRIM($G132))=LOWER(TRIM($F132)),"Match","Mismatch")) | I132: =IF($G132="","",IF(LOWER(TRIM($G132))=LOWER(TRIM($E132)),"Match","Mismatch"))
A133: Bad OCR | B133: Hayganoush_Khodagholian.pdf | C133: Environmental / Social | D133: Has the patient fallen in the last year | E133: Yes | F133: No | H133: =IF($G133="","",IF(LOWER(TRIM($G133))=LOWER(TRIM($F133)),"Match","Mismatch")) | I133: =IF($G133="","",IF(LOWER(TRIM($G133))=LOWER(TRIM($E133)),"Match","Mismatch"))
...

Sheet Summary by Field
A1: Mandatory review threshold (Gemini match rate must be ≥ this to skip review): | D1: 0.9
A3: Section | B3: Field | C3: Rows Spot-Checked | D3: Rows Reviewed So Far | E3: Gemini Match Rate | F3: Cloud Vision Match Rate | G3: Mandatory Review?
A4: Behavioral Observations | B4: Agitation/Aggression: Does the patient get angry or hostile | C4: =COUNTIFS('Spot Check'!$C:$C,$A4,'Spot Check'!$D:$D,$B4) -> 16 | D4: =COUNTIFS('Spot Check'!$C:$C,$A4,'Spot Check'!$D:$D,$B4,'Spot Check'!$G:$G,"<>") -> 0 | E4: =IFERROR(COUNTIFS('Spot Check'!$C:$C,$A4,'Spot Check'!$D:$D,$B4,'Spot Check'!$H:$H,"Match")/$D4,"") | F4: =IFERROR(COUNTIFS('Spot Check'!$C:$C,$A4,'Spot Check'!$D:$D,$B4,'Spot Check'!$I:$I,"Match")/$D4,"") | G4: =IF($D4=0,"Not yet reviewed",IF($E4<$D$1,"Yes — below threshold","No")) -> Not yet reviewed
A5: Behavioral Observations | B5: Anxiety/Shadowing: Does the patient routinely follow around their caregiver | C5: =COUNTIFS('Spot Check'!$C:$C,$A5,'Spot Check'!$D:$D,$B5) -> 17 | D5: =COUNTIFS('Spot Check'!$C:$C,$A5,'Spot Check'!$D:$D,$B5,'Spot Check'!$G:$G,"<>") -> 0 | E5: =IFERROR(COUNTIFS('Spot Check'!$C:$C,$A5,'Spot Check'!$D:$D,$B5,'Spot Check'!$H:$H,"Match")/$D5,"") | F5: =IFERROR(COUNTIFS('Spot Check'!$C:$C,$A5,'Spot Check'!$D:$D,$B5,'Spot Check'!$I:$I,"Match")/$D5,"") | G5: =IF($D5=0,"Not yet reviewed",IF($E5<$D$1,"Yes — below threshold","No")) -> Not yet reviewed
A6: Behavioral Observations | B6: Hallucinations: Does the patient see and/or hear things that no one else can see or hear | C6: =COUNTIFS('Spot Check'!$C:$C,$A6,'Spot Check'!$D:$D,$B6) -> 20 | D6: =COUNTIFS('Spot Check'!$C:$C,$A6,'Spot Check'!$D:$D,$B6,'Spot Check'!$G:$G,"<>") -> 0 | E6: =IFERROR(COUNTIFS('Spot Check'!$C:$C,$A6,'Spot Check'!$D:$D,$B6,'Spot Check'!$H:$H,"Match")/$D6,"") | F6: =IFERROR(COUNTIFS('Spot Check'!$C:$C,$A6,'Spot Check'!$D:$D,$B6,'Spot Check'!$I:$I,"Match")/$D6,"") | G6: =IF($D6=0,"Not yet reviewed",IF($E6<$D$1,"Yes — below threshold","No")) -> Not yet reviewed
A7: Behavioral Observations | B7: Indifference/Social Withdrawal: Does the patient seem less interested in their usual activities | C7: =COUNTIFS('Spot Check'!$C:$C,$A7,'Spot Check'!$D:$D,$B7) -> 15 | D7: =COUNTIFS('Spot Check'!$C:$C,$A7,'Spot Check'!$D:$D,$B7,'Spot Check'!$G:$G,"<>") -> 0 | E7: =IFERROR(COUNTIFS('Spot Check'!$C:$C,$A7,'Spot Check'!$D:$D,$B7,'Spot Check'!$H:$H,"Match")/$D7,"") | F7: =IFERROR(COUNTIFS('Spot Check'!$C:$C,$A7,'Spot Check'!$D:$D,$B7,'Spot Check'!$I:$I,"Match")/$D7,"") | G7: =IF($D7=0,"Not yet reviewed",IF($E7<$D$1,"Yes — below threshold","No")) -> Not yet reviewed
A8: Behavioral Observations | B8: Irritability/Moodiness: Does the patient act impatient | C8: =COUNTIFS('Spot Check'!$C:$C,$A8,'Spot Check'!$D:$D,$B8) -> 15 | D8: =COUNTIFS('Spot Check'!$C:$C,$A8,'Spot Check'!$D:$D,$B8,'Spot Check'!$G:$G,"<>") -> 0 | E8: =IFERROR(COUNTIFS('Spot Check'!$C:$C,$A8,'Spot Check'!$D:$D,$B8,'Spot Check'!$H:$H,"Match")/$D8,"") | F8: =IFERROR(COUNTIFS('Spot Check'!$C:$C,$A8,'Spot Check'!$D:$D,$B8,'Spot Check'!$I:$I,"Match")/$D8,"") | G8: =IF($D8=0,"Not yet reviewed",IF($E8<$D$1,"Yes — below threshold","No")) -> Not yet reviewed
A9: Behavioral Observations | B9: Other Behavioral Observations | C9: =COUNTIFS('Spot Check'!$C:$C,$A9,'Spot Check'!$D:$D,$B9) -> 22 | D9: =COUNTIFS('Spot Check'!$C:$C,$A9,'Spot Check'!$D:$D,$B9,'Spot Check'!$G:$G,"<>") -> 0 | E9: =IFERROR(COUNTIFS('Spot Check'!$C:$C,$A9,'Spot Check'!$D:$D,$B9,'Spot Check'!$H:$H,"Match")/$D9,"") | F9: =IFERROR(COUNTIFS('Spot Check'!$C:$C,$A9,'Spot Check'!$D:$D,$B9,'Spot Check'!$I:$I,"Match")/$D9,"") | G9: =IF($D9=0,"Not yet reviewed",IF($E9<$D$1,"Yes — below threshold","No")) -> Not yet reviewed
A10: Behavioral Observations | B10: Sleep Problems: Does the patient have trouble sleeping at night | C10: =COUNTIFS('Spot Check'!$C:$C,$A10,'Spot Check'!$D:$D,$B10) -> 18 | D10: =COUNTIFS('Spot Check'!$C:$C,$A10,'Spot Check'!$D:$D,$B10,'Spot Check'!$G:$G,"<>") -> 0 | E10: =IFERROR(COUNTIFS('Spot Check'!$C:$C,$A10,'Spot Check'!$D:$D,$B10,'Spot Check'!$H:$H,"Match")/$D10,"") | F10: =IFERROR(COUNTIFS('Spot Check'!$C:$C,$A10,'Spot Check'!$D:$D,$B10,'Spot Check'!$I:$I,"Match")/$D10,"") | G10: =IF($D10=0,"Not yet reviewed",IF($E10<$D$1,"Yes — below threshold","No")) -> Not yet reviewed
A11: Behavioral Observations | B11: Suspiciousness/Paranoia: Is the patient suspicious without good reason | C11: =COUNTIFS('Spot Check'!$C:$C,$A11,'Spot Check'!$D:$D,$B11) -> 19 | D11: =COUNTIFS('Spot Check'!$C:$C,$A11,'Spot Check'!$D:$D,$B11,'Spot Check'!$G:$G,"<>") -> 0 | E11: =IFERROR(COUNTIFS('Spot Check'!$C:$C,$A11,'Spot Check'!$D:$D,$B11,'Spot Check'!$H:$H,"Match")/$D11,"") | F11: =IFERROR(COUNTIFS('Spot Check'!$C:$C,$A11,'Spot Check'!$D:$D,$B11,'Spot Check'!$I:$I,"Match")/$D11,"") | G11: =IF($D11=0,"Not yet reviewed",IF($E11<$D$1,"Yes — below threshold","No")) -> Not yet reviewed
A12: Daily Function (rating scale) | B12: Bathing | C12: =COUNTIFS('Spot Check'!$C:$C,$A12,'Spot Check'!$D:$D,$B12) -> 19 | D12: =COUNTIFS('Spot Check'!$C:$C,$A12,'Spot Check'!$D:$D,$B12,'Spot Check'!$G:$G,"<>") -> 0 | E12: =IFERROR(COUNTIFS('Spot Check'!$C:$C,$A12,'Spot Check'!$D:$D,$B12,'Spot Check'!$H:$H,"Match")/$D12,"") | F12: =IFERROR(COUNTIFS('Spot Check'!$C:$C,$A12,'Spot Check'!$D:$D,$B12,'Spot Check'!$I:$I,"Match")/$D12,"") | G12: =IF($D12=0,"Not yet reviewed",IF($E12<$D$1,"Yes — below threshold","No")) -> Not yet reviewed
A13: Daily Function (rating scale) | B13: Continence (control of bladder and bowels) | C13: =COUNTIFS('Spot Check'!$C:$C,$A13,'Spot Check'!$D:$D,$B13) -> 23 | D13: =COUNTIFS('Spot Check'!$C:$C,$A13,'Spot Check'!$D:$D,$B13,'Spot Check'!$G:$G,"<>") -> 0 | E13: =IFERROR(COUNTIFS('Spot Check'!$C:$C,$A13,'Spot Check'!$D:$D,$B13,'Spot Check'!$H:$H,"Match")/$D13,"") | F13: =IFERROR(COUNTIFS('Spot Check'!$C:$C,$A13,'Spot Check'!$D:$D,$B13,'Spot Check'!$I:$I,"Match")/$D13,"") | G13: =IF($D13=0,"Not yet reviewed",IF($E13<$D$1,"Yes — below threshold","No")) -> Not yet reviewed
A14: Daily Function (rating scale) | B14: Dressing (including getting clothes from drawers or closet) | C14: =COUNTIFS('Spot Check'!$C:$C,$A14,'Spot Check'!$D:$D,$B14) -> 20 | D14: =COUNTIFS('Spot Check'!$C:$C,$A14,'Spot Check'!$D:$D,$B14,'Spot Check'!$G:$G,"<>") -> 0 | E14: =IFERROR(COUNTIFS('Spot Check'!$C:$C,$A14,'Spot Check'!$D:$D,$B14,'Spot Check'!$H:$H,"Match")/$D14,"") | F14: =IFERROR(COUNTIFS('Spot Check'!$C:$C,$A14,'Spot Check'!$D:$D,$B14,'Spot Check'!$I:$I,"Match")/$D14,"") | G14: =IF($D14=0,"Not yet reviewed",IF($E14<$D$1,"Yes — below threshold","No")) -> Not yet reviewed
A15: Daily Function (rating scale) | B15: Driving or using public transportation | C15: =COUNTIFS('Spot Check'!$C:$C,$A15,'Spot Check'!$D:$D,$B15) -> 17 | D15: =COUNTIFS('Spot Check'!$C:$C,$A15,'Spot Check'!$D:$D,$B15,'Spot Check'!$G:$G,"<>") -> 0 | E15: =IFERROR(COUNTIFS('Spot Check'!$C:$C,$A15,'Spot Check'!$D:$D,$B15,'Spot Check'!$H:$H,"Match")/$D15,"") | F15: =IFERROR(COUNTIFS('Spot Check'!$C:$C,$A15,'Spot Check'!$D:$D,$B15,'Spot Check'!$I:$I,"Match")/$D15,"") | G15: =IF($D15=0,"Not yet reviewed",IF($E15<$D$1,"Yes — below threshold","No")) -> Not yet reviewed
... A41: Header / Identifying Info | B41: Referral Date: | C41: =COUNTIFS('Spot Check'!$C:$C,$A41,'Spot Check'!$D:$D,$B41) -> 25 | D41: =COUNTIFS('Spot Check'!$C:$C,$A41,'Spot Check'!$D:$D,$B41,'Spot Check'!$G:$G,"<>") -> 0 | E41: =IFERROR(COUNTIFS('Spot Check'!$C:$C,$A41,'Spot Check'!$D:$D,$B41,'Spot Check'!$H:$H,"Match")/$D41,"") | F41: =IFERROR(COUNTIFS('Spot Check'!$C:$C,$A41,'Spot Check'!$D:$D,$B41,'Spot Check'!$I:$I,"Match")/$D41,"") | G41: =IF($D41=0,"Not yet reviewed",IF($E41<$D$1,"Yes — below threshold","No")) -> Not yet reviewed
